{
	"configurations" : 
	[
		{
			"directories" : 
			[
				{
					"build" : ".",
					"jsonFile" : "directory-.-RelWithDebInfo-d0094a50bb2071803777.json",
					"minimumCMakeVersion" : 
					{
						"string" : "3.6.0"
					},
					"projectIndex" : 0,
					"source" : ".",
					"targetIndexes" : 
					[
						0
					]
				}
			],
			"name" : "RelWithDebInfo",
			"projects" : 
			[
				{
					"directoryIndexes" : 
					[
						0
					],
					"name" : "MyAppNative",
					"targetIndexes" : 
					[
						0
					]
				}
			],
			"targets" : 
			[
				{
					"directoryIndex" : 0,
					"id" : "native-lib::@6890427a1f51a3e7e1df",
					"jsonFile" : "target-native-lib-RelWithDebInfo-8a06672992caabf59be9.json",
					"name" : "native-lib",
					"projectIndex" : 0
				}
			]
		}
	],
	"kind" : "codemodel",
	"paths" : 
	{
		"build" : "C:/Developement/mc_bitbucket/app/.cxx/RelWithDebInfo/6dk4j3bh/armeabi-v7a",
		"source" : "C:/Developement/mc_bitbucket/app/src/main/cpp"
	},
	"version" : 
	{
		"major" : 2,
		"minor" : 3
	}
}
